jy_lib/__init__.py
jy_lib/auth_client.py
jy_lib/bank.py
jy_lib/base.py
jy_lib/cache.py
jy_lib/clickhouse.py
jy_lib/compressor.py
jy_lib/country.py
jy_lib/currency.py
jy_lib/date.py
jy_lib/decorator.py
jy_lib/exchange.py
jy_lib/forex.py
jy_lib/interrupt_protect.py
jy_lib/lock.py
jy_lib/math.py
jy_lib/nav.py
jy_lib/parquets.py
jy_lib/reader.py
jy_lib/smb_client.py
jy_lib/symbol.py
jy_lib/symbol_em.py
jy_lib/time.py
jy_lib/xt_ws_client.py
jy_lib-1.0.2.dist-info/LICENSE
jy_lib-1.0.2.dist-info/WHEEL
jy_lib-1.0.2.dist-info/METADATA
jy_lib-1.0.2.dist-info/RECORD
