Metadata-Version: 2.1
Name: jy_lib
Version: 1.0.2
Summary: Python SDK for jyfund
Author-email: jyfund <popsars@gmail.com>
Requires-Dist: loguru
Requires-Dist: pysmb
Requires-Dist: websockets
Requires-Dist: brotli
Requires-Dist: humanize
Requires-Dist: lz4
Requires-Dist: pypinyin
Requires-Dist: zstandard
Requires-Dist: clickhouse_driver
Requires-Dist: clickhouse-cityhash
Requires-Dist: polars
Requires-Dist: requests
Requires-Dist: fs
Requires-Dist: fs.smbfs
